arkose/__init__.py
arkose/api.py
arkose/crypt.py
arkose/fingerprint.py
arkose/murmur.py
arkose/session.py
arkose/utils.py
arkose-2.0.1.dist-info/LICENSE
arkose-2.0.1.dist-info/METADATA
arkose-2.0.1.dist-info/WHEEL
arkose-2.0.1.dist-info/top_level.txt
arkose-2.0.1.dist-info/RECORD
