Metadata-Version: 2.1
Name: arkose
Version: 2.0.1
Summary: A Python package to interact with Funcaptcha (Arkose Labs)
Home-page: https://github.com/Micxzy/arkose
Author: Micxzy
Author-email: no@dont.email.me
License: MIT
Classifier: Programming Language :: Python :: 3
Classifier: License :: OSI Approved :: MIT License
Classifier: Operating System :: OS Independent
Requires-Python: >=3.6
License-File: LICENSE
Requires-Dist: aiohttp
Requires-Dist: requests
Requires-Dist: pycryptodome
